recursiveai/benchmark/__init__.py
recursiveai/benchmark/_internal/__init__.py
recursiveai/benchmark/_internal/_benchmark_evaluator.py
recursiveai/benchmark/_internal/_benchmark_output.py
recursiveai/benchmark/_internal/_criteria_evaluator.py
recursiveai/benchmark/_internal/_evaluation.py
recursiveai/benchmark/_internal/_run_output.py
recursiveai/benchmark/_internal/_evaluators/__init__.py
recursiveai/benchmark/_internal/_evaluators/_happy.py
recursiveai/benchmark/_internal/_evaluators/_llm_criteria_judge.py
recursiveai/benchmark/_internal/_evaluators/_llm_criteria_jury.py
recursiveai/benchmark/_internal/_evaluators/_llm_judge.py
recursiveai/benchmark/_internal/_evaluators/_llm_jury.py
recursiveai/benchmark/_internal/_evaluators/_regex_match.py
recursiveai/benchmark/_internal/_evaluators/_strict_match.py
recursiveai/benchmark/_internal/_llm/_anthropic_claude_model.py
recursiveai/benchmark/_internal/_llm/_azure_openai_gpt_model.py
recursiveai/benchmark/_internal/_llm/_google_gemini_model.py
recursiveai/benchmark/_internal/_llm/_llm_model.py
recursiveai/benchmark/_internal/_llm/_openai_gpt_model.py
recursiveai/benchmark/_internal/_metrics/_benchmark_metrics.py
recursiveai/benchmark/_internal/_metrics/_run_metrics.py
recursiveai/benchmark/_internal/_util/__init__.py
recursiveai/benchmark/api/__init__.py
recursiveai/benchmark/api/benchmark.py
recursiveai/benchmark/api/benchmark_agent.py
recursiveai/benchmark/api/benchmark_case.py
recursiveai/benchmark/api/benchmark_evaluator.py
recursiveai/benchmark/api/benchmark_run.py
recursiveai/benchmark/api/benchmark_runner.py
recursiveai/benchmark/api/exit_code.py
recursiveai/benchmark/api/agents/__init__.py
recursiveai/benchmark/api/agents/async_callback_agent.py
recursiveai/benchmark/api/agents/callback_agent.py
recursiveai/benchmark/api/util/__init__.py
flow_benchmark_tools-1.5.0.dist-info/METADATA
flow_benchmark_tools-1.5.0.dist-info/WHEEL
flow_benchmark_tools-1.5.0.dist-info/top_level.txt
flow_benchmark_tools-1.5.0.dist-info/RECORD
