Metadata-Version: 2.2
Name: flow-benchmark-tools
Version: 1.5.0
Summary: A library containing LLM benchmarking tools
Project-URL: homepage, https://github.com/recursiveai/flow_benchmark_tools
Requires-Python: <3.12,>=3.8
Requires-Dist: pydantic~=2.0
Requires-Dist: openai~=1.29
Requires-Dist: numpy~=1.26
Requires-Dist: anthropic>=0.29.0
Requires-Dist: google-generativeai~=0.7
Provides-Extra: dev
Requires-Dist: pytest==8.2.0; extra == "dev"
Requires-Dist: pytest-cov==5.0.0; extra == "dev"
Requires-Dist: pytest-asyncio==0.23.6; extra == "dev"
Requires-Dist: pytest-rerunfailures==14.0; extra == "dev"
Requires-Dist: pytest-xdist==3.6.1; extra == "dev"
Requires-Dist: pylint==3.2.0; extra == "dev"
Requires-Dist: pyright==1.1.363; extra == "dev"
Requires-Dist: bandit==1.7.8; extra == "dev"
Requires-Dist: black==24.4.2; extra == "dev"
Requires-Dist: isort==5.13.2; extra == "dev"
Requires-Dist: pre-commit==3.7.1; extra == "dev"
Provides-Extra: pub
Requires-Dist: build==1.2.1; extra == "pub"
Requires-Dist: twine==5.1.1; extra == "pub"
Provides-Extra: examples
Requires-Dist: langchain==0.3.25; extra == "examples"
Requires-Dist: langchain-community==0.3.24; extra == "examples"
Requires-Dist: langchain-openai==0.3.19; extra == "examples"
Requires-Dist: langchain-google-genai==2.0.10; extra == "examples"
Requires-Dist: pypdf==4.2.0; extra == "examples"
Requires-Dist: docx2txt==0.8; extra == "examples"
Requires-Dist: faiss-cpu==1.7.4; extra == "examples"
